LICENSE
README.md
setup.py
openai_maas/__init__.py
openai_maas/openai_maas.py
openai_maas.egg-info/PKG-INFO
openai_maas.egg-info/SOURCES.txt
openai_maas.egg-info/dependency_links.txt
openai_maas.egg-info/requires.txt
openai_maas.egg-info/top_level.txt
openai_maas/fonts/Impacted.ttf
openai_maas/fonts/impact.ttf
openai_maas/fonts/impact.zip
openai_maas/fonts/sharefonts.net.txt
openai_maas/fonts/unicode.impact.ttf